homebase_package/__init__.py
homebase_package/homebase.py
homebase_whatware-1.0.dist-info/LICENSE
homebase_whatware-1.0.dist-info/METADATA
homebase_whatware-1.0.dist-info/WHEEL
homebase_whatware-1.0.dist-info/top_level.txt
homebase_whatware-1.0.dist-info/RECORD
