Metadata-Version: 2.1
Name: homebase-whatware
Version: 1.0
Summary: a simple python app that has lots of basic functions.
Home-page: https://github.com/whatwareweb/homebase
Author: kidney bean
Author-email: kidneybean6938@protonmail.com
License: UNKNOWN
Project-URL: Bug Tracker, https://github.com/whatwareweb/homebase/issues
Platform: UNKNOWN
Classifier: Programming Language :: Python :: 3
Classifier: License :: OSI Approved :: MIT License
Classifier: Operating System :: OS Independent
Requires-Python: >=3.6
License-File: LICENSE
